CHANGELOG
README.txt
setup.py
submodal/__init__.py
submodal/release.py
submodal/widgets.py
submodal.egg-info/PKG-INFO
submodal.egg-info/SOURCES.txt
submodal.egg-info/dependency_links.txt
submodal.egg-info/entry_points.txt
submodal.egg-info/not-zip-safe
submodal.egg-info/requires.txt
submodal.egg-info/top_level.txt
submodal/static/css/style.css
submodal/static/css/subModal.css
submodal/static/html/loading.html
submodal/static/html/testing.html
submodal/static/images/close.gif
submodal/static/images/loading.gif
submodal/static/javascript/subModal.js
submodal/static/javascript/submodalsource.js
