Metadata-Version: 1.0
Name: submodal
Version: 1.5
Summary: Cross Browser DHTML Modal Dialogs For Web Apps
Home-page: http://gabrito.com/post/enhancements-to-submodal
Author: Jorge Godoy (packager)
Author-email: jgodoy@gmail.com
License: Free for any use - See included files
Keywords: turbogears.widgets
Platform: UNKNOWN
Classifier: Development Status :: 3 - Alpha
Classifier: Operating System :: OS Independent
Classifier: Programming Language :: Python
Classifier: Topic :: Software Development :: Libraries :: Python Modules
Classifier: Framework :: TurboGears
Classifier: Framework :: TurboGears :: Widgets
